tppi/__init__.py
tppi/org.py
tppi/protocol.py
pytppi-0.2.dist-info/LICENSE.txt
pytppi-0.2.dist-info/METADATA
pytppi-0.2.dist-info/WHEEL
pytppi-0.2.dist-info/top_level.txt
pytppi-0.2.dist-info/RECORD
