Metadata-Version: 2.1
Name: pytppi
Version: 0.2
Summary: tppi stands for Tilde Pipe Plus Interface
Author: Abhijit Bose (aka. boseji)
Project-URL: Homepage, https://github.com/boseji/pytppi
Project-URL: Repository, https://github.com/boseji/pytppi.git
Project-URL: Issues, https://github.com/boseji/pytppi/issues
Keywords: communication,encoding,string,iot,industrial
Classifier: Development Status :: 5 - Production/Stable
Classifier: Topic :: Communications
Classifier: Topic :: Home Automation
Classifier: Topic :: Internet
Classifier: License :: OSI Approved :: Apache Software License
Classifier: Programming Language :: Python :: 3
Classifier: Programming Language :: Python :: 3.8
Classifier: Programming Language :: Python :: 3.9
Requires-Python: >=3.8
License-File: LICENSE.txt
Provides-Extra: dev
Requires-Dist: build ; extra == 'dev'
Requires-Dist: coverage ; extra == 'dev'
Requires-Dist: black ; extra == 'dev'
